minio_keygen/__init__.py
minio_keygen/functions.py
minio_keygen/main.py
minio_keygen/version.py
minio_keygen/tests/__init__.py
minio_keygen/tests/test_minio_keygen.py
minio_keygen-1.0.1.dist-info/LICENSE
minio_keygen-1.0.1.dist-info/METADATA
minio_keygen-1.0.1.dist-info/WHEEL
minio_keygen-1.0.1.dist-info/entry_points.txt
minio_keygen-1.0.1.dist-info/top_level.txt
minio_keygen-1.0.1.dist-info/RECORD
